{
    "os": "Linux-5.4.0-172-generic-x86_64-with-glibc2.31",
    "python": "3.11.9",
    "heartbeatAt": "2024-05-31T15:54:11.251423",
    "startedAt": "2024-05-31T15:54:09.635967",
    "docker": null,
    "cuda": null,
    "args": [],
    "state": "running",
    "program": "/hpi/fs00/home/jim.maar/interpretability/training_probes.py",
    "codePath": "training_probes.py",
    "git": {
        "remote": "https://github.com/Jim-Maar/interpretability.git",
        "commit": "982b10a5f9ff860e6e012828595e39bf8fc014f5"
    },
    "email": "jimmaar1@Gmail.com",
    "root": "/hpi/fs00/home/jim.maar/interpretability",
    "host": "gx01",
    "username": "jim.maar",
    "executable": "/hpi/fs00/home/jim.maar/miniconda3/envs/othello-env/bin/python",
    "cpu_count": 128,
    "cpu_count_logical": 256,
    "cpu_freq": {
        "current": 3086.59069921875,
        "min": 1500.0,
        "max": 2250.0
    },
    "cpu_freq_per_core": [
        {
            "current": 3392.045,
            "min": 1500.0,
            "max": 2250.0
        },
        {
            "current": 3221.316,
            "min": 1500.0,
            "max": 2250.0
        },
        {
            "current": 3384.636,
            "min": 1500.0,
            "max": 2250.0
        },
        {
            "current": 3326.417,
            "min": 1500.0,
            "max": 2250.0
        },
        {
            "current": 2636.237,
            "min": 1500.0,
            "max": 2250.0
        },
        {
            "current": 1733.079,
            "min": 1500.0,
            "max": 2250.0
        },
        {
            "current": 2678.596,
            "min": 1500.0,
            "max": 2250.0
        },
        {
            "current": 1730.803,
            "min": 1500.0,
            "max": 2250.0
        },
        {
            "current": 3349.794,
            "min": 1500.0,
            "max": 2250.0
        },
        {
            "current": 2660.796,
            "min": 1500.0,
            "max": 2250.0
        },
        {
            "current": 1734.158,
            "min": 1500.0,
            "max": 2250.0
        },
        {
            "current": 2524.296,
            "min": 1500.0,
            "max": 2250.0
        },
        {
            "current": 1729.583,
            "min": 1500.0,
            "max": 2250.0
        },
        {
            "current": 2667.296,
            "min": 1500.0,
            "max": 2250.0
        },
        {
            "current": 2664.293,
            "min": 1500.0,
            "max": 2250.0
        },
        {
            "current": 3383.945,
            "min": 1500.0,
            "max": 2250.0
        },
        {
            "current": 2151.18,
            "min": 1500.0,
            "max": 2250.0
        },
        {
            "current": 3384.57,
            "min": 1500.0,
            "max": 2250.0
        },
        {
            "current": 3390.991,
            "min": 1500.0,
            "max": 2250.0
        },
        {
            "current": 3120.014,
            "min": 1500.0,
            "max": 2250.0
        },
        {
            "current": 1736.442,
            "min": 1500.0,
            "max": 2250.0
        },
        {
            "current": 2670.124,
            "min": 1500.0,
            "max": 2250.0
        },
        {
            "current": 1736.436,
            "min": 1500.0,
            "max": 2250.0
        },
        {
            "current": 2663.627,
            "min": 1500.0,
            "max": 2250.0
        },
        {
            "current": 3391.012,
            "min": 1500.0,
            "max": 2250.0
        },
        {
            "current": 3390.023,
            "min": 1500.0,
            "max": 2250.0
        },
        {
            "current": 3392.137,
            "min": 1500.0,
            "max": 2250.0
        },
        {
            "current": 3394.117,
            "min": 1500.0,
            "max": 2250.0
        },
        {
            "current": 3395.956,
            "min": 1500.0,
            "max": 2250.0
        },
        {
            "current": 3390.005,
            "min": 1500.0,
            "max": 2250.0
        },
        {
            "current": 3389.668,
            "min": 1500.0,
            "max": 2250.0
        },
        {
            "current": 3387.984,
            "min": 1500.0,
            "max": 2250.0
        },
        {
            "current": 3391.732,
            "min": 1500.0,
            "max": 2250.0
        },
        {
            "current": 3391.86,
            "min": 1500.0,
            "max": 2250.0
        },
        {
            "current": 3390.774,
            "min": 1500.0,
            "max": 2250.0
        },
        {
            "current": 3393.461,
            "min": 1500.0,
            "max": 2250.0
        },
        {
            "current": 1862.808,
            "min": 1500.0,
            "max": 2250.0
        },
        {
            "current": 3117.441,
            "min": 1500.0,
            "max": 2250.0
        },
        {
            "current": 2024.243,
            "min": 1500.0,
            "max": 2250.0
        },
        {
            "current": 3170.907,
            "min": 1500.0,
            "max": 2250.0
        },
        {
            "current": 3391.322,
            "min": 1500.0,
            "max": 2250.0
        },
        {
            "current": 3382.086,
            "min": 1500.0,
            "max": 2250.0
        },
        {
            "current": 3353.76,
            "min": 1500.0,
            "max": 2250.0
        },
        {
            "current": 3389.562,
            "min": 1500.0,
            "max": 2250.0
        },
        {
            "current": 3090.62,
            "min": 1500.0,
            "max": 2250.0
        },
        {
            "current": 3110.369,
            "min": 1500.0,
            "max": 2250.0
        },
        {
            "current": 2566.854,
            "min": 1500.0,
            "max": 2250.0
        },
        {
            "current": 3386.566,
            "min": 1500.0,
            "max": 2250.0
        },
        {
            "current": 3387.11,
            "min": 1500.0,
            "max": 2250.0
        },
        {
            "current": 3381.309,
            "min": 1500.0,
            "max": 2250.0
        },
        {
            "current": 2775.148,
            "min": 1500.0,
            "max": 2250.0
        },
        {
            "current": 3395.712,
            "min": 1500.0,
            "max": 2250.0
        },
        {
            "current": 3360.164,
            "min": 1500.0,
            "max": 2250.0
        },
        {
            "current": 3080.777,
            "min": 1500.0,
            "max": 2250.0
        },
        {
            "current": 2208.13,
            "min": 1500.0,
            "max": 2250.0
        },
        {
            "current": 2209.804,
            "min": 1500.0,
            "max": 2250.0
        },
        {
            "current": 2244.137,
            "min": 1500.0,
            "max": 2250.0
        },
        {
            "current": 2228.465,
            "min": 1500.0,
            "max": 2250.0
        },
        {
            "current": 3388.951,
            "min": 1500.0,
            "max": 2250.0
        },
        {
            "current": 2221.344,
            "min": 1500.0,
            "max": 2250.0
        },
        {
            "current": 3389.536,
            "min": 1500.0,
            "max": 2250.0
        },
        {
            "current": 3397.329,
            "min": 1500.0,
            "max": 2250.0
        },
        {
            "current": 2230.468,
            "min": 1500.0,
            "max": 2250.0
        },
        {
            "current": 3392.3,
            "min": 1500.0,
            "max": 2250.0
        },
        {
            "current": 2422.8,
            "min": 1500.0,
            "max": 2250.0
        },
        {
            "current": 3384.778,
            "min": 1500.0,
            "max": 2250.0
        },
        {
            "current": 2535.383,
            "min": 1500.0,
            "max": 2250.0
        },
        {
            "current": 2836.788,
            "min": 1500.0,
            "max": 2250.0
        },
        {
            "current": 2864.109,
            "min": 1500.0,
            "max": 2250.0
        },
        {
            "current": 3383.459,
            "min": 1500.0,
            "max": 2250.0
        },
        {
            "current": 3386.745,
            "min": 1500.0,
            "max": 2250.0
        },
        {
            "current": 3385.815,
            "min": 1500.0,
            "max": 2250.0
        },
        {
            "current": 3384.073,
            "min": 1500.0,
            "max": 2250.0
        },
        {
            "current": 1776.595,
            "min": 1500.0,
            "max": 2250.0
        },
        {
            "current": 3402.471,
            "min": 1500.0,
            "max": 2250.0
        },
        {
            "current": 3408.432,
            "min": 1500.0,
            "max": 2250.0
        },
        {
            "current": 3400.825,
            "min": 1500.0,
            "max": 2250.0
        },
        {
            "current": 1698.156,
            "min": 1500.0,
            "max": 2250.0
        },
        {
            "current": 1696.904,
            "min": 1500.0,
            "max": 2250.0
        },
        {
            "current": 1691.154,
            "min": 1500.0,
            "max": 2250.0
        },
        {
            "current": 2476.774,
            "min": 1500.0,
            "max": 2250.0
        },
        {
            "current": 3325.129,
            "min": 1500.0,
            "max": 2250.0
        },
        {
            "current": 2282.15,
            "min": 1500.0,
            "max": 2250.0
        },
        {
            "current": 1693.593,
            "min": 1500.0,
            "max": 2250.0
        },
        {
            "current": 2333.048,
            "min": 1500.0,
            "max": 2250.0
        },
        {
            "current": 3385.803,
            "min": 1500.0,
            "max": 2250.0
        },
        {
            "current": 1689.514,
            "min": 1500.0,
            "max": 2250.0
        },
        {
            "current": 1698.109,
            "min": 1500.0,
            "max": 2250.0
        },
        {
            "current": 1744.354,
            "min": 1500.0,
            "max": 2250.0
        },
        {
            "current": 1748.865,
            "min": 1500.0,
            "max": 2250.0
        },
        {
            "current": 1759.866,
            "min": 1500.0,
            "max": 2250.0
        },
        {
            "current": 2372.912,
            "min": 1500.0,
            "max": 2250.0
        },
        {
            "current": 2407.245,
            "min": 1500.0,
            "max": 2250.0
        },
        {
            "current": 2350.107,
            "min": 1500.0,
            "max": 2250.0
        },
        {
            "current": 2329.617,
            "min": 1500.0,
            "max": 2250.0
        },
        {
            "current": 2330.55,
            "min": 1500.0,
            "max": 2250.0
        },
        {
            "current": 3392.249,
            "min": 1500.0,
            "max": 2250.0
        },
        {
            "current": 2307.575,
            "min": 1500.0,
            "max": 2250.0
        },
        {
            "current": 3376.836,
            "min": 1500.0,
            "max": 2250.0
        },
        {
            "current": 3326.353,
            "min": 1500.0,
            "max": 2250.0
        },
        {
            "current": 1581.173,
            "min": 1500.0,
            "max": 2250.0
        },
        {
            "current": 2542.153,
            "min": 1500.0,
            "max": 2250.0
        },
        {
            "current": 1741.518,
            "min": 1500.0,
            "max": 2250.0
        },
        {
            "current": 1740.882,
            "min": 1500.0,
            "max": 2250.0
        },
        {
            "current": 2525.477,
            "min": 1500.0,
            "max": 2250.0
        },
        {
            "current": 2467.942,
            "min": 1500.0,
            "max": 2250.0
        },
        {
            "current": 2455.286,
            "min": 1500.0,
            "max": 2250.0
        },
        {
            "current": 3380.111,
            "min": 1500.0,
            "max": 2250.0
        },
        {
            "current": 2501.428,
            "min": 1500.0,
            "max": 2250.0
        },
        {
            "current": 2528.427,
            "min": 1500.0,
            "max": 2250.0
        },
        {
            "current": 3370.705,
            "min": 1500.0,
            "max": 2250.0
        },
        {
            "current": 2490.102,
            "min": 1500.0,
            "max": 2250.0
        },
        {
            "current": 1745.218,
            "min": 1500.0,
            "max": 2250.0
        },
        {
            "current": 2534.726,
            "min": 1500.0,
            "max": 2250.0
        },
        {
            "current": 3241.565,
            "min": 1500.0,
            "max": 2250.0
        },
        {
            "current": 1741.57,
            "min": 1500.0,
            "max": 2250.0
        },
        {
            "current": 2451.829,
            "min": 1500.0,
            "max": 2250.0
        },
        {
            "current": 3390.946,
            "min": 1500.0,
            "max": 2250.0
        },
        {
            "current": 2530.365,
            "min": 1500.0,
            "max": 2250.0
        },
        {
            "current": 2430.524,
            "min": 1500.0,
            "max": 2250.0
        },
        {
            "current": 3389.59,
            "min": 1500.0,
            "max": 2250.0
        },
        {
            "current": 1693.014,
            "min": 1500.0,
            "max": 2250.0
        },
        {
            "current": 2534.687,
            "min": 1500.0,
            "max": 2250.0
        },
        {
            "current": 2421.177,
            "min": 1500.0,
            "max": 2250.0
        },
        {
            "current": 1791.368,
            "min": 1500.0,
            "max": 2250.0
        },
        {
            "current": 1791.547,
            "min": 1500.0,
            "max": 2250.0
        },
        {
            "current": 1796.707,
            "min": 1500.0,
            "max": 2250.0
        },
        {
            "current": 1791.688,
            "min": 1500.0,
            "max": 2250.0
        },
        {
            "current": 3383.788,
            "min": 1500.0,
            "max": 2250.0
        },
        {
            "current": 3391.002,
            "min": 1500.0,
            "max": 2250.0
        },
        {
            "current": 3390.089,
            "min": 1500.0,
            "max": 2250.0
        },
        {
            "current": 3391.093,
            "min": 1500.0,
            "max": 2250.0
        },
        {
            "current": 2421.563,
            "min": 1500.0,
            "max": 2250.0
        },
        {
            "current": 2436.38,
            "min": 1500.0,
            "max": 2250.0
        },
        {
            "current": 1742.813,
            "min": 1500.0,
            "max": 2250.0
        },
        {
            "current": 3121.355,
            "min": 1500.0,
            "max": 2250.0
        },
        {
            "current": 3389.559,
            "min": 1500.0,
            "max": 2250.0
        },
        {
            "current": 2461.268,
            "min": 1500.0,
            "max": 2250.0
        },
        {
            "current": 3398.385,
            "min": 1500.0,
            "max": 2250.0
        },
        {
            "current": 3390.129,
            "min": 1500.0,
            "max": 2250.0
        },
        {
            "current": 2946.179,
            "min": 1500.0,
            "max": 2250.0
        },
        {
            "current": 3383.262,
            "min": 1500.0,
            "max": 2250.0
        },
        {
            "current": 3387.546,
            "min": 1500.0,
            "max": 2250.0
        },
        {
            "current": 3396.856,
            "min": 1500.0,
            "max": 2250.0
        },
        {
            "current": 3389.847,
            "min": 1500.0,
            "max": 2250.0
        },
        {
            "current": 3386.931,
            "min": 1500.0,
            "max": 2250.0
        },
        {
            "current": 3392.989,
            "min": 1500.0,
            "max": 2250.0
        },
        {
            "current": 3382.136,
            "min": 1500.0,
            "max": 2250.0
        },
        {
            "current": 3389.761,
            "min": 1500.0,
            "max": 2250.0
        },
        {
            "current": 3389.651,
            "min": 1500.0,
            "max": 2250.0
        },
        {
            "current": 3387.703,
            "min": 1500.0,
            "max": 2250.0
        },
        {
            "current": 3395.182,
            "min": 1500.0,
            "max": 2250.0
        },
        {
            "current": 3378.706,
            "min": 1500.0,
            "max": 2250.0
        },
        {
            "current": 3381.982,
            "min": 1500.0,
            "max": 2250.0
        },
        {
            "current": 3389.28,
            "min": 1500.0,
            "max": 2250.0
        },
        {
            "current": 3397.104,
            "min": 1500.0,
            "max": 2250.0
        },
        {
            "current": 3390.468,
            "min": 1500.0,
            "max": 2250.0
        },
        {
            "current": 3388.776,
            "min": 1500.0,
            "max": 2250.0
        },
        {
            "current": 3390.926,
            "min": 1500.0,
            "max": 2250.0
        },
        {
            "current": 3392.726,
            "min": 1500.0,
            "max": 2250.0
        },
        {
            "current": 3389.455,
            "min": 1500.0,
            "max": 2250.0
        },
        {
            "current": 3390.792,
            "min": 1500.0,
            "max": 2250.0
        },
        {
            "current": 3390.926,
            "min": 1500.0,
            "max": 2250.0
        },
        {
            "current": 3385.636,
            "min": 1500.0,
            "max": 2250.0
        },
        {
            "current": 2464.833,
            "min": 1500.0,
            "max": 2250.0
        },
        {
            "current": 3349.101,
            "min": 1500.0,
            "max": 2250.0
        },
        {
            "current": 2296.196,
            "min": 1500.0,
            "max": 2250.0
        },
        {
            "current": 2454.218,
            "min": 1500.0,
            "max": 2250.0
        },
        {
            "current": 1694.529,
            "min": 1500.0,
            "max": 2250.0
        },
        {
            "current": 1692.202,
            "min": 1500.0,
            "max": 2250.0
        },
        {
            "current": 3402.333,
            "min": 1500.0,
            "max": 2250.0
        },
        {
            "current": 2402.095,
            "min": 1500.0,
            "max": 2250.0
        },
        {
            "current": 2226.846,
            "min": 1500.0,
            "max": 2250.0
        },
        {
            "current": 2406.078,
            "min": 1500.0,
            "max": 2250.0
        },
        {
            "current": 1695.226,
            "min": 1500.0,
            "max": 2250.0
        },
        {
            "current": 3405.018,
            "min": 1500.0,
            "max": 2250.0
        },
        {
            "current": 2388.448,
            "min": 1500.0,
            "max": 2250.0
        },
        {
            "current": 2399.091,
            "min": 1500.0,
            "max": 2250.0
        },
        {
            "current": 3396.34,
            "min": 1500.0,
            "max": 2250.0
        },
        {
            "current": 2392.549,
            "min": 1500.0,
            "max": 2250.0
        },
        {
            "current": 2507.818,
            "min": 1500.0,
            "max": 2250.0
        },
        {
            "current": 1742.219,
            "min": 1500.0,
            "max": 2250.0
        },
        {
            "current": 1748.05,
            "min": 1500.0,
            "max": 2250.0
        },
        {
            "current": 1743.924,
            "min": 1500.0,
            "max": 2250.0
        },
        {
            "current": 2464.844,
            "min": 1500.0,
            "max": 2250.0
        },
        {
            "current": 2458.07,
            "min": 1500.0,
            "max": 2250.0
        },
        {
            "current": 2450.959,
            "min": 1500.0,
            "max": 2250.0
        },
        {
            "current": 2448.694,
            "min": 1500.0,
            "max": 2250.0
        },
        {
            "current": 2443.347,
            "min": 1500.0,
            "max": 2250.0
        },
        {
            "current": 2458.07,
            "min": 1500.0,
            "max": 2250.0
        },
        {
            "current": 2453.511,
            "min": 1500.0,
            "max": 2250.0
        },
        {
            "current": 2450.392,
            "min": 1500.0,
            "max": 2250.0
        },
        {
            "current": 3385.714,
            "min": 1500.0,
            "max": 2250.0
        },
        {
            "current": 3387.552,
            "min": 1500.0,
            "max": 2250.0
        },
        {
            "current": 3372.365,
            "min": 1500.0,
            "max": 2250.0
        },
        {
            "current": 3389.834,
            "min": 1500.0,
            "max": 2250.0
        },
        {
            "current": 2870.05,
            "min": 1500.0,
            "max": 2250.0
        },
        {
            "current": 2355.53,
            "min": 1500.0,
            "max": 2250.0
        },
        {
            "current": 3375.65,
            "min": 1500.0,
            "max": 2250.0
        },
        {
            "current": 3395.529,
            "min": 1500.0,
            "max": 2250.0
        },
        {
            "current": 3390.637,
            "min": 1500.0,
            "max": 2250.0
        },
        {
            "current": 3388.469,
            "min": 1500.0,
            "max": 2250.0
        },
        {
            "current": 2400.8,
            "min": 1500.0,
            "max": 2250.0
        },
        {
            "current": 3384.469,
            "min": 1500.0,
            "max": 2250.0
        },
        {
            "current": 3387.283,
            "min": 1500.0,
            "max": 2250.0
        },
        {
            "current": 3401.654,
            "min": 1500.0,
            "max": 2250.0
        },
        {
            "current": 3381.719,
            "min": 1500.0,
            "max": 2250.0
        },
        {
            "current": 3390.267,
            "min": 1500.0,
            "max": 2250.0
        },
        {
            "current": 3370.484,
            "min": 1500.0,
            "max": 2250.0
        },
        {
            "current": 2379.59,
            "min": 1500.0,
            "max": 2250.0
        },
        {
            "current": 3392.985,
            "min": 1500.0,
            "max": 2250.0
        },
        {
            "current": 3382.17,
            "min": 1500.0,
            "max": 2250.0
        },
        {
            "current": 3394.011,
            "min": 1500.0,
            "max": 2250.0
        },
        {
            "current": 3392.57,
            "min": 1500.0,
            "max": 2250.0
        },
        {
            "current": 3390.219,
            "min": 1500.0,
            "max": 2250.0
        },
        {
            "current": 3392.561,
            "min": 1500.0,
            "max": 2250.0
        },
        {
            "current": 3379.414,
            "min": 1500.0,
            "max": 2250.0
        },
        {
            "current": 3393.102,
            "min": 1500.0,
            "max": 2250.0
        },
        {
            "current": 3406.173,
            "min": 1500.0,
            "max": 2250.0
        },
        {
            "current": 3386.884,
            "min": 1500.0,
            "max": 2250.0
        },
        {
            "current": 3404.599,
            "min": 1500.0,
            "max": 2250.0
        },
        {
            "current": 3384.699,
            "min": 1500.0,
            "max": 2250.0
        },
        {
            "current": 3388.013,
            "min": 1500.0,
            "max": 2250.0
        },
        {
            "current": 3402.113,
            "min": 1500.0,
            "max": 2250.0
        },
        {
            "current": 3391.318,
            "min": 1500.0,
            "max": 2250.0
        },
        {
            "current": 3399.811,
            "min": 1500.0,
            "max": 2250.0
        },
        {
            "current": 3405.774,
            "min": 1500.0,
            "max": 2250.0
        },
        {
            "current": 3382.547,
            "min": 1500.0,
            "max": 2250.0
        },
        {
            "current": 2415.168,
            "min": 1500.0,
            "max": 2250.0
        },
        {
            "current": 3394.918,
            "min": 1500.0,
            "max": 2250.0
        },
        {
            "current": 2221.314,
            "min": 1500.0,
            "max": 2250.0
        },
        {
            "current": 2375.96,
            "min": 1500.0,
            "max": 2250.0
        },
        {
            "current": 3385.144,
            "min": 1500.0,
            "max": 2250.0
        },
        {
            "current": 3382.713,
            "min": 1500.0,
            "max": 2250.0
        },
        {
            "current": 3381.454,
            "min": 1500.0,
            "max": 2250.0
        },
        {
            "current": 1965.246,
            "min": 1500.0,
            "max": 2250.0
        },
        {
            "current": 3380.372,
            "min": 1500.0,
            "max": 2250.0
        },
        {
            "current": 3376.949,
            "min": 1500.0,
            "max": 2250.0
        },
        {
            "current": 3392.955,
            "min": 1500.0,
            "max": 2250.0
        },
        {
            "current": 3390.276,
            "min": 1500.0,
            "max": 2250.0
        },
        {
            "current": 3400.107,
            "min": 1500.0,
            "max": 2250.0
        },
        {
            "current": 3386.704,
            "min": 1500.0,
            "max": 2250.0
        },
        {
            "current": 3396.011,
            "min": 1500.0,
            "max": 2250.0
        },
        {
            "current": 3388.654,
            "min": 1500.0,
            "max": 2250.0
        },
        {
            "current": 2421.999,
            "min": 1500.0,
            "max": 2250.0
        },
        {
            "current": 3395.269,
            "min": 1500.0,
            "max": 2250.0
        },
        {
            "current": 2376.582,
            "min": 1500.0,
            "max": 2250.0
        },
        {
            "current": 3009.208,
            "min": 1500.0,
            "max": 2250.0
        },
        {
            "current": 3395.376,
            "min": 1500.0,
            "max": 2250.0
        },
        {
            "current": 2548.187,
            "min": 1500.0,
            "max": 2250.0
        },
        {
            "current": 2516.947,
            "min": 1500.0,
            "max": 2250.0
        },
        {
            "current": 2316.236,
            "min": 1500.0,
            "max": 2250.0
        },
        {
            "current": 3401.269,
            "min": 1500.0,
            "max": 2250.0
        },
        {
            "current": 2552.6,
            "min": 1500.0,
            "max": 2250.0
        },
        {
            "current": 2544.452,
            "min": 1500.0,
            "max": 2250.0
        },
        {
            "current": 2513.508,
            "min": 1500.0,
            "max": 2250.0
        }
    ],
    "disk": {
        "total": 1757.7545127868652,
        "used": 115.4472770690918
    },
    "gpu": "NVIDIA A100-SXM4-40GB",
    "gpu_count": 1,
    "gpu_devices": [
        {
            "name": "NVIDIA A100-SXM4-40GB",
            "memory_total": 42949672960
        }
    ],
    "memory": {
        "total": 1007.6792068481445
    }
}
